{
  "iso": "nl",
  "name": "Netherlands",
  "full_name": "Netherlands – Kingdom of the Netherlands",
  "meta": {
    "date": 1619649472601
  },
  "results": {
    "innovations": [],
    "publishers": [],
    "ogp_commitments": [
      {
        "ogp_commitment": "OGP National Action Plan 2018-20",
        "ogp_commitment_link": "https://www.opengovpartnership.org/sites/default/files/Netherlands_Action-Plan_2018-2020_Short_NL.pdf"
      },
      {
        "ogp_commitment": "OGP National Action Plan 2020-22",
        "ogp_commitment_link": "https://www.opengovpartnership.org/wp-content/uploads/2021/01/Netherlands_Action-Plan_2020-2022.pdf"
      }
    ],
    "ocds_description": "United States"
  }
}