{
  "iso": "pe",
  "name": "Peru",
  "full_name": "Peru – Republic of Peru",
  "meta": {
    "date": 1616016793898
  },
  "results": {
    "innovations": [
      {
        "innovation_description": "Perú Observa: Observatorio de Compras Públicas",
        "innovation_link": "https://www.perucompras.gob.pe/observatorio/indicadores-acuerdos-marco.php"
      }
    ],
    "publishers": [
      {
        "publisher": "Peru Compras",
        "publisher_link": "https://www.catalogos.perucompras.gob.pe/ConsultaOrdenesPub",
        "ocds_historic_data": false,
        "ocds_ongoing_data": true,
        "ocds_implementation": false,
        "year_first_implemented": "2020"
      },
      {
        "publisher": "",
        "publisher_link": "",
        "ocds_historic_data": false,
        "ocds_ongoing_data": false,
        "ocds_implementation": false,
        "year_first_implemented": ""
      }
    ],
    "ogp_commitments": [
      {
        "ogp_commitment": "National Government Open Data Strategy of Peru 2017 - 2021",
        "ogp_commitment_link": "https://sgp.pcm.gob.pe/wp-content/uploads/2017/05/Modelo-y-Estrategia-DAG-del-Peru.pdf"
      }
    ],
    "disclosure_oil_mining": "partial",
    "disclosure_oil_mining_description": "Most or all"
  }
}